simplebot_mastodon/__init__.py
simplebot_mastodon/_version.py
simplebot_mastodon/mastodon-logo.png
simplebot_mastodon/migrations.py
simplebot_mastodon/orm.py
simplebot_mastodon/util.py
simplebot_mastodon-0.6.1.dist-info/licenses/LICENSE
simplebot_mastodon-0.6.1.dist-info/METADATA
simplebot_mastodon-0.6.1.dist-info/WHEEL
simplebot_mastodon-0.6.1.dist-info/entry_points.txt
simplebot_mastodon-0.6.1.dist-info/top_level.txt
simplebot_mastodon-0.6.1.dist-info/RECORD
