Metadata-Version: 2.4
Name: simplebot_mastodon
Version: 0.6.1
Summary: Mastodon/DeltaChat bridge.
Home-page: https://github.com/simplebot-org/simplebot_mastodon
Author: adbenitez
Author-email: adb@arcanechat.me
License: MPL
Keywords: simplebot plugin deltachat mastodon bridge
Classifier: Development Status :: 4 - Beta
Classifier: Environment :: Plugins
Classifier: Programming Language :: Python :: 3
Classifier: License :: OSI Approved :: Mozilla Public License 2.0 (MPL 2.0)
Classifier: Operating System :: OS Independent
Classifier: Topic :: Utilities
Requires-Python: >=3.10
License-File: LICENSE
Requires-Dist: simplebot>=4.2.0
Requires-Dist: Mastodon.py>=2.0.1
Requires-Dist: html2text>=2024.2.26
Requires-Dist: beautifulsoup4>=4.13.3
Requires-Dist: requests>=2.32.3
Requires-Dist: pydub>=0.25.1
Requires-Dist: SQLAlchemy>=2.0.39
Provides-Extra: test
Requires-Dist: pytest>=8.3.5; extra == "test"
Provides-Extra: dev
Requires-Dist: simplebot>=4.2.0; extra == "dev"
Requires-Dist: Mastodon.py>=2.0.1; extra == "dev"
Requires-Dist: html2text>=2024.2.26; extra == "dev"
Requires-Dist: beautifulsoup4>=4.13.3; extra == "dev"
Requires-Dist: requests>=2.32.3; extra == "dev"
Requires-Dist: pydub>=0.25.1; extra == "dev"
Requires-Dist: SQLAlchemy>=2.0.39; extra == "dev"
Requires-Dist: pytest>=8.3.5; extra == "dev"
Requires-Dist: black>=25.1.0; extra == "dev"
Requires-Dist: mypy>=1.15.0; extra == "dev"
Requires-Dist: isort>=6.0.1; extra == "dev"
Requires-Dist: pylint>=3.3.6; extra == "dev"
Requires-Dist: pylama>=8.4.1; extra == "dev"
Requires-Dist: types-requests>=2.32.0.20250306; extra == "dev"
Requires-Dist: setuptools; extra == "dev"
Dynamic: author
Dynamic: author-email
Dynamic: classifier
Dynamic: description
Dynamic: description-content-type
Dynamic: home-page
Dynamic: keywords
Dynamic: license
Dynamic: license-file
Dynamic: provides-extra
Dynamic: requires-dist
Dynamic: requires-python
Dynamic: summary
